[
	{
		"n": 1,
		"texto": "Que tipo de lugar você acha que reflete mais a sua personalidade e te deixaria mais à vontade?"
	},	
	{
		"n": 2,
		"texto": "Que tipo de animal te chama mais a atenção (não necessariamente é seu preferido)?"
	},
	{
		"n": 3,
		"texto": "Se tivesse que escolher uma arma para entrar em combate que tipo lhe chamaria mais atenção?"
    },
	{
		"n": 4,
		"texto": "Um xingamento ou zoação que seria provável fazerem com você?"
    },
    {
		"n": 5,
		"texto": "Qual você diria que são adjetivos possivelmente mais aplicáveis a você?"
    },
    {
		"n": 6,
		"texto": "Quais seriam seus defeitos mais destacáveis?"
    },
    {
		"n": 7,
		"texto": "Em se tratando de jogos e práticas esportivas você:"
    },
    {
		"n": 8,
		"texto": "Em uma festa você provavelmente:"
    },
    {
		"n": 9,
		"texto": "Qual desses poderes especiais você acharia mais interessante ter?"
    },
    {
		"n": 10,
		"texto": "Assinale as opções que as palavras mais chamam a sua atenção!"
    },
    {
		"n": 11,
		"texto": "Que ditos populares chamam mais sua atenção?"
	}
]